zc/sourcefactory/README.txt
zc/sourcefactory/__init__.py
zc/sourcefactory/adapters.py
zc/sourcefactory/adapters.txt
zc/sourcefactory/basic.py
zc/sourcefactory/configure-z2.zcml
zc/sourcefactory/configure.zcml
zc/sourcefactory/constructors.txt
zc/sourcefactory/contextual.py
zc/sourcefactory/factories.py
zc/sourcefactory/ftesting.zcml
zc/sourcefactory/interfaces.py
zc/sourcefactory/mapping.py
zc/sourcefactory/mapping.txt
zc/sourcefactory/named.py
zc/sourcefactory/policies.py
zc/sourcefactory/source.py
zc/sourcefactory/tests.py
zc/sourcefactory/browser/README.txt
zc/sourcefactory/browser/__init__.py
zc/sourcefactory/browser/configure.zcml
zc/sourcefactory/browser/mapping.py
zc/sourcefactory/browser/source.py
zc/sourcefactory/browser/tests.py
zc/sourcefactory/browser/token.py
zc/sourcefactory/browser/token.txt
zc_sourcefactory-3.0.dist-info/licenses/LICENSE.txt
zc_sourcefactory-3.0.dist-info/METADATA
zc_sourcefactory-3.0.dist-info/WHEEL
zc_sourcefactory-3.0.dist-info/top_level.txt
zc_sourcefactory-3.0.dist-info/RECORD
