Metadata-Version: 2.4
Name: zc.sourcefactory
Version: 3.0
Summary: An easy way to create custom Zope sources.
Home-page: https://github.com/zopefoundation/zc.sourcefactory
Author: Zope Foundation and Contributors
Author-email: zope-dev@zope.dev
License: ZPL-2.1
Keywords: zope vocabulary source factory
Classifier: Topic :: Software Development
Classifier: Framework :: Zope :: 3
Classifier: Framework :: Zope :: 4
Classifier: Development Status :: 5 - Production/Stable
Classifier: Intended Audience :: Developers
Classifier: License :: OSI Approved :: Zope Public License
Classifier: Programming Language :: Python
Classifier: Programming Language :: Python :: 3
Classifier: Programming Language :: Python :: 3.9
Classifier: Programming Language :: Python :: 3.10
Classifier: Programming Language :: Python :: 3.11
Classifier: Programming Language :: Python :: 3.12
Classifier: Programming Language :: Python :: 3.13
Classifier: Programming Language :: Python :: Implementation :: CPython
Classifier: Natural Language :: English
Classifier: Operating System :: OS Independent
Requires-Python: >=3.9
License-File: LICENSE.txt
Requires-Dist: ZODB
Requires-Dist: persistent
Requires-Dist: setuptools
Requires-Dist: zope.intid
Requires-Dist: zope.browser
Requires-Dist: zope.component
Requires-Dist: zope.dublincore
Requires-Dist: zope.interface
Requires-Dist: zope.proxy
Requires-Dist: zope.publisher
Requires-Dist: zope.schema
Provides-Extra: test
Requires-Dist: zope.component[zcml]; extra == "test"
Requires-Dist: persistent>=4.4.3; extra == "test"
Requires-Dist: zope.site; extra == "test"
Requires-Dist: zope.testing; extra == "test"
Requires-Dist: zope.testrunner>=6.4; extra == "test"
Requires-Dist: zope.keyreference; extra == "test"
Dynamic: author
Dynamic: author-email
Dynamic: classifier
Dynamic: description
Dynamic: home-page
Dynamic: keywords
Dynamic: license
Dynamic: license-file
Dynamic: provides-extra
Dynamic: requires-dist
Dynamic: requires-python
Dynamic: summary
